{
  "id": "github-hexstrike-ai",
  "registry": "github",
  "language": "python",
  "source_tier": "community",
  "archive_size_bytes": 2074513,
  "duration_s": 1.62,
  "download_seconds": 0.24,
  "scan_seconds": 1.38,
  "capability_vector": {
    "filesystem": {
      "detected": true,
      "confidence": "low",
      "depth_raw": 2.0,
      "depth_adjusted": 1.0
    },
    "shell": {
      "detected": true,
      "confidence": "high",
      "depth_raw": 10,
      "depth_adjusted": 10.0
    },
    "egress": {
      "detected": true,
      "confidence": "high",
      "depth_raw": 8,
      "depth_adjusted": 8.0
    },
    "ingress": {
      "detected": true,
      "confidence": "high",
      "depth_raw": 1,
      "depth_adjusted": 1.0
    },
    "secrets": {
      "detected": false,
      "confidence": "low",
      "depth_raw": 0.0,
      "depth_adjusted": 0.0
    },
    "delegation": {
      "detected": false,
      "confidence": "low",
      "depth_raw": 0.0,
      "depth_adjusted": 0.0
    },
    "impersonation": {
      "detected": true,
      "confidence": "high",
      "depth_raw": 6,
      "depth_adjusted": 6.0
    },
    "data_sensitivity": {
      "detected": true,
      "confidence": "high",
      "depth_raw": 4,
      "depth_adjusted": 4.0
    }
  },
  "score": {
    "breadth": 75.0,
    "depth": 37.5,
    "exposure": 0.0,
    "provenance": 35.0,
    "attack_surface_score": 37.12
  },
  "extractor_version": "0.1.0",
  "score_function_version": "1.0"
}